dynuipv4update/README.MD
dynuipv4update/__init__.py
dynuipv4update/requirements.txt
dynuipv4update/thirdparty.json
dynuipv4update-0.12.dist-info/LICENSE.rst
dynuipv4update-0.12.dist-info/METADATA
dynuipv4update-0.12.dist-info/WHEEL
dynuipv4update-0.12.dist-info/top_level.txt
dynuipv4update-0.12.dist-info/RECORD
