Metadata-Version: 2.1
Name: dynuipv4update
Version: 0.12
Summary: Updates the Dynamic DNS (DDNS) record for a given subdomain and domain using the Dynu API
Home-page: https://github.com/hansalemaos/dynuipv4update
Author: Johannes Fischer
Author-email: aulasparticularesdealemaosp@gmail.com
License: MIT
Keywords: dynamic,ddns
Classifier: Development Status :: 4 - Beta
Classifier: Programming Language :: Python :: 3 :: Only
Classifier: Programming Language :: Python :: 3.10
Classifier: Topic :: Software Development :: Libraries :: Python Modules
Classifier: Topic :: Utilities
License-File: LICENSE.rst
Requires-Dist: getpublicipv4
Requires-Dist: kthread
Requires-Dist: kthread-sleep
Requires-Dist: pfehler
Requires-Dist: requests
